specidentify/__init__.py
specidentify/_astropy_init.py
specidentify/arcwidget.py
specidentify/conftest.py
specidentify/gingatools.py
specidentify/guitools.py
specidentify/interidentify.py
specidentify/iterfit.py
specidentify/spectools.py
specidentify/version.py
specidentify/wavelengthsolution.py
specidentify/tests/__init__.py
specidentify/tests/setup_package.py
specidentify/tests/test_spectools.py
specidentify-0.1.0.dist-info/LICENSE.rst
specidentify-0.1.0.dist-info/METADATA
specidentify-0.1.0.dist-info/WHEEL
specidentify-0.1.0.dist-info/top_level.txt
specidentify-0.1.0.dist-info/RECORD
