Metadata-Version: 2.1
Name: specidentify
Version: 0.1.0
Summary: Specidentify is for identifying spectral lines and calibrating spectroscopic observations
Home-page: https://github.com/crawfordsm/specidentify
Author: Steven M. Crwford
Author-email: crawfordsm@gmail.com
License: BSD 3-Clause
Platform: UNKNOWN
Requires-Python: >=3.7
Requires-Dist: astropy
Requires-Dist: numpy
Requires-Dist: scipy
Requires-Dist: specutils
Requires-Dist: matplotlib
Requires-Dist: ipywidgets
Requires-Dist: pyspectrograph
Provides-Extra: docs
Requires-Dist: sphinx-astropy ; extra == 'docs'
Provides-Extra: test
Requires-Dist: pytest-astropy ; extra == 'test'
